Metadata-Version: 1.0
Name: dash-editor-components
Version: 0.0.2
Summary: Code Editor components for Dash
Home-page: UNKNOWN
Author: Dawid Kopczyk <dawid.kopczyk@quantee.ai>
Author-email: UNKNOWN
License: MIT
Platform: UNKNOWN
